LICENSE
MANIFEST.in
README
setup.py
kph/__init__.py
kph.egg-info/PKG-INFO
kph.egg-info/SOURCES.txt
kph.egg-info/dependency_links.txt
kph.egg-info/top_level.txt