Metadata-Version: 1.1
Name: kph
Version: 0.4.1
Summary: Python 2/3 ready implementation of the Koelner Phonetic.
Home-page: https://github.com/mherrmann/kph
Author: Robert Schindler
Author-email: r.schindler@efficiosoft.com
License: GPL-3
Platform: UNKNOWN
Classifier: Development Status :: 5 - Production/Stable
Classifier: Intended Audience :: Developers
Classifier: License :: OSI Approved :: GNU General Public License (GPL)
Classifier: Natural Language :: English
Classifier: Operating System :: OS Independent
Classifier: Programming Language :: Python
Classifier: Topic :: Software Development :: Libraries :: Python Modules
